{
  "__type__": "cc.Mesh",
  "_name": "",
  "_objFlags": 0,
  "__editorExtras__": {},
  "_native": ".bin",
  "_struct": {
    "primitives": [
      {
        "primitiveMode": 7,
        "jointMapIndex": 0,
        "vertexBundelIndices": [
          0
        ],
        "indexView": {
          "offset": 58896,
          "length": 6468,
          "count": 3234,
          "stride": 2
        }
      }
    ],
    "vertexBundles": [
      {
        "view": {
          "offset": 0,
          "length": 58896,
          "count": 818,
          "stride": 72
        },
        "attributes": [
          {
            "name": "a_position",
            "format": 32,
            "isNormalized": false
          },
          {
            "name": "a_normal",
            "format": 32,
            "isNormalized": false
          },
          {
            "name": "a_texCoord",
            "format": 21,
            "isNormalized": false
          },
          {
            "name": "a_tangent",
            "format": 44,
            "isNormalized": false
          },
          {
            "name": "a_joints",
            "format": 42,
            "isNormalized": false
          },
          {
            "name": "a_weights",
            "format": 44,
            "isNormalized": false
          }
        ]
      }
    ],
    "minPosition": {
      "__type__": "cc.Vec3",
      "x": -0.8688488006591797,
      "y": -0.0018162999767810106,
      "z": -2.486204147338867
    },
    "maxPosition": {
      "__type__": "cc.Vec3",
      "x": 0.8688490390777588,
      "y": 3.3773703575134277,
      "z": 2.486204147338867
    },
    "jointMaps": [
      [
        0,
        1,
        2,
        3,
        4,
        5,
        6,
        7,
        8,
        9,
        10,
        11,
        12,
        13,
        14,
        15,
        16,
        17,
        18,
        19,
        20,
        21,
        22,
        23,
        24,
        25,
        26
      ]
    ]
  },
  "_hash": 1360446230,
  "_allowDataAccess": true
}